tpds/__init__.py
tpds/certs/__init__.py
tpds/certs/cert.py
tpds/certs/cert_utils.py
tpds/certs/certs_backup.py
tpds/certs/create_cert_defs.py
tpds/certs/ext_builder.py
tpds/certs/sign_csr.py
tpds/certs/sign_csr.zip
tpds/certs/tflex_certs.py
tpds/certs/timefix_backend.py
tpds/certs/wpc_cert_def.py
tpds/certs/x509_find_elements.py
tpds/certs/sign_csr/readme.md
tpds/certs/sign_csr/requirements.txt
tpds/certs/sign_csr/sign_csr.py
tpds/cloud_connect/__init__.py
tpds/cloud_connect/aws_connect.py
tpds/cloud_connect/azureRTOS_connect.py
tpds/cloud_connect/azure_connect.py
tpds/cloud_connect/azure_sdk.py
tpds/cloud_connect/cloud_connect.py
tpds/cloud_connect/gcp_connect.py
tpds/flash_program/__init__.py
tpds/flash_program/flash_program.py
tpds/flash_program/kit_connect.py
tpds/manifest/__init__.py
tpds/manifest/manifest.py
tpds/manifest/tflx_manifest.py
tpds/manifest/tng_manifest.py
tpds/output_grabber/__init__.py
tpds/output_grabber/library_output_grabber.py
tpds/proto_provision/__init__.py
tpds/proto_provision/ecc204_provision.py
tpds/proto_provision/ecc_provision.py
tpds/proto_provision/proto_provision.py
tpds/proto_provision/sha10x_provision.py
tpds/proto_provision/ta010_provision.py
tpds/proto_provision/tflxtls_provision.py
tpds/proto_provision/tflxwpc_provision.py
tpds/pubkey_validation/__init__.py
tpds/pubkey_validation/device_pubkey_validation.py
tpds/pubkey_validation/pubkey_validation.py
tpds/resource_generation/__init__.py
tpds/resource_generation/resource_generation.py
tpds/resource_generation/tflx_resource_generation.py
tpds/resource_generation/tng_manifest_generation.py
tpds/secure_element/__init__.py
tpds/secure_element/ca_element.py
tpds/secure_element/constants.py
tpds/secure_element/ecc204.py
tpds/secure_element/ecc608a.py
tpds/secure_element/sha10x.py
tpds/secure_element/sha204a.py
tpds/secure_element/sha206a.py
tpds/secure_element/ta010.py
tpds/ta_attribute_parser/__init__.py
tpds/ta_attribute_parser/attr_common.py
tpds_helper-2.3.23.dist-info/licenses/LICENSE
tpds_helper-2.3.23.dist-info/METADATA
tpds_helper-2.3.23.dist-info/WHEEL
tpds_helper-2.3.23.dist-info/top_level.txt
tpds_helper-2.3.23.dist-info/RECORD
