Metadata-Version: 2.4
Name: tpds-helper
Version: 2.3.23
Summary: Microchip(SPG) Trust Platform Utilities
Maintainer-email: Microchip Technology <SPG.Tools@microchip.com>
License: (c) 2018-2021 Microchip Technology Inc. and its subsidiaries.
Classifier: License :: Other/Proprietary License
Classifier: Development Status :: 4 - Beta
Classifier: Programming Language :: Python :: 3
Classifier: Operating System :: OS Independent
Requires-Python: >=3.8
License-File: LICENSE
Requires-Dist: asn1crypto
Requires-Dist: cryptography~=35.0.0
Requires-Dist: hidapi
Requires-Dist: ipycanvas~=0.13.3
Requires-Dist: ipython
Requires-Dist: ipywidgets~=8.0.2
Requires-Dist: lxml
Requires-Dist: pyasn1_modules
Requires-Dist: Pygments
Requires-Dist: pykitinfo==1.1.2.19
Requires-Dist: pymcuprog
Requires-Dist: pyOpenSSL~=22.0.0
Requires-Dist: python_jose
Requires-Dist: PyYAML
Requires-Dist: libusb_package
Requires-Dist: websocket_client
Requires-Dist: awscli
Requires-Dist: tpds-certificate-tools
Requires-Dist: tpds-schema
Requires-Dist: cryptoauthlib>=20241015
Requires-Dist: requests
Provides-Extra: azure
Requires-Dist: azure-iot-hub; extra == "azure"
Requires-Dist: azure-identity; extra == "azure"
Requires-Dist: azure-mgmt-iothub; extra == "azure"
Requires-Dist: azure-iot-device; extra == "azure"
Requires-Dist: azure-iothub-provisioningserviceclient; extra == "azure"
Requires-Dist: azure-mgmt-iothubprovisioningservices; extra == "azure"
Requires-Dist: azure-mgmt-resource; extra == "azure"
Provides-Extra: dev
Requires-Dist: flake8; extra == "dev"
Requires-Dist: black; extra == "dev"
Requires-Dist: isort; extra == "dev"
Requires-Dist: mypy; extra == "dev"
Provides-Extra: test
Requires-Dist: pytest-cov; extra == "test"
Requires-Dist: pytest-mock; extra == "test"
Requires-Dist: pytest-integration; extra == "test"
Dynamic: license-file
